typedload/__init__.py
typedload/__init__.pyi
typedload/alias.py
typedload/datadumper.py
typedload/dataloader.py
typedload/exceptions.py
typedload/helpers.py
typedload/py.typed
typedload/typechecks.py
typedload-2.39.dist-info/licenses/LICENSE
typedload-2.39.dist-info/METADATA
typedload-2.39.dist-info/WHEEL
typedload-2.39.dist-info/top_level.txt
typedload-2.39.dist-info/RECORD
