Metadata-Version: 2.4
Name: typedload
Version: 2.39
Summary: Load and dump data from json-like format into typed data structures
Home-page: https://ltworf.codeberg.page/typedload/
Author: Salvo 'LtWorf' Tomaselli
Author-email: Salvo 'LtWorf' Tomaselli <tiposchi@tiscali.it>
License: This software is released under the GNU General Public License 3.
Project-URL: Homepage, https://ltworf.codeberg.page/typedload/
Project-URL: Bug Tracker, https://codeberg.org/ltworf/typedload/issues
Keywords: typing,types,mypy,json,schema,json-schema,python3,namedtuple,enums,dataclass,pydantic
Classifier: Development Status :: 5 - Production/Stable
Classifier: Intended Audience :: Developers
Classifier: License :: OSI Approved :: GNU General Public License v3 (GPLv3)
Classifier: Typing :: Typed
Classifier: Programming Language :: Python :: 3.10
Classifier: Programming Language :: Python :: 3.11
Classifier: Programming Language :: Python :: 3.12
Classifier: Programming Language :: Python :: 3.13
Classifier: Programming Language :: Python :: 3.14
Requires-Python: >=3.10
License-File: LICENSE
Dynamic: author
Dynamic: home-page
Dynamic: license-file
